{
		"frames":[
			
			{
			"res":"FD7D0115",
			"x":0,
			"y":0
			},
			{
			"res":"7AE9B3E1",
			"x":0,
			"y":0
			},
			{
			"res":"4A37BDCB",
			"x":0,
			"y":0
			},
			{
			"res":"7AE9B3E1",
			"x":0,
			"y":0
			},
			{
			"res":"FD7D0115",
			"x":0,
			"y":0
			},
			{
			"res":"7AE9B3E1",
			"x":0,
			"y":0
			},
			{
			"res":"4A37BDCB",
			"x":0,
			"y":0
			},
			{
			"res":"7AE9B3E1",
			"x":0,
			"y":0
			},
			{
			"res":"FD7D0115",
			"x":0,
			"y":0
			},
			{
			"res":"7AE9B3E1",
			"x":0,
			"y":0
			},
			{
			"res":"4A37BDCB",
			"x":0,
			"y":0
			}
			],
	"res":{
		"FD7D0115":{"x":0,"y":0,"w":283,"h":215},
		"4A37BDCB":{"x":0,"y":215,"w":283,"h":215},
		"7AE9B3E1":{"x":283,"y":0,"w":283,"h":215}
	}}