[
  {
    "ID": 0,
    "相性": 22
  },
  {
    "ID": 1,
    "相性": 36
  },
  {
    "ID": 2,
    "相性": 25,
    "标签": ["乐"]
  },
  {
    "ID": 3,
    "相性": 24
  },
  {
    "ID": 4,
    "相性": 25
  },
  {
    "ID": 5,
    "相性": 79
  },
  {
    "ID": 6,
    "相性": 143
  },
  {
    "ID": 7,
    "相性": 79
  },
  {
    "ID": 8,
    "相性": 140
  },
  {
    "ID": 9,
    "相性": 69
  },
  {
    "ID": 10,
    "相性": 126
  },
  {
    "ID": 11,
    "相性": 69
  },
  {
    "ID": 12,
    "相性": 66
  },
  {
    "ID": 14,
    "相性": 1
  },
  {
    "ID": 15,
    "相性": 1
  },
  {
    "ID": 16,
    "相性": 149
  },
  {
    "ID": 17,
    "相性": 8
  },
  {
    "ID": 18,
    "相性": 110
  },
  {
    "ID": 19,
    "相性": 101
  },
  {
    "ID": 20,
    "相性": 27
  },
  {
    "ID": 21,
    "相性": 142
  },
  {
    "ID": 22,
    "相性": 65
  },
  {
    "ID": 23,
    "相性": 65
  },
  {
    "ID": 24,
    "相性": 65
  },
  {
    "ID": 25,
    "相性": 75
  },
  {
    "ID": 26,
    "相性": 1
  },
  {
    "ID": 27,
    "相性": 111
  },
  {
    "ID": 28,
    "相性": 126
  },
  {
    "ID": 29,
    "相性": 93
  },
  {
    "ID": 30,
    "相性": 48
  },
  {
    "ID": 31,
    "相性": 149
  },
  {
    "ID": 32,
    "相性": 1
  },
  {
    "ID": 33,
    "相性": 88
  },
  {
    "ID": 34,
    "相性": 127
  },
  {
    "ID": 35,
    "相性": 56
  },
  {
    "ID": 36,
    "相性": 45
  },
  {
    "ID": 37,
    "相性": 140
  },
  {
    "ID": 38,
    "相性": 20
  },
  {
    "ID": 39,
    "相性": 96
  },
  {
    "ID": 40,
    "相性": 43
  },
  {
    "ID": 41,
    "相性": 35
  },
  {
    "ID": 42,
    "相性": 138
  },
  {
    "ID": 43,
    "相性": 1
  },
  {
    "ID": 44,
    "相性": 1
  },
  {
    "ID": 45,
    "相性": 146
  },
  {
    "ID": 46,
    "相性": 75
  },
  {
    "ID": 47,
    "相性": 45
  },
  {
    "ID": 48,
    "相性": 36
  },
  {
    "ID": 49,
    "相性": 25
  },
  {
    "ID": 50,
    "相性": 55
  },
  {
    "ID": 51,
    "相性": 11
  },
  {
    "ID": 52,
    "相性": 75
  },
  {
    "ID": 53,
    "相性": 145
  },
  {
    "ID": 55,
    "相性": 70
  },
  {
    "ID": 56,
    "相性": 77
  },
  {
    "ID": 57,
    "相性": 1
  },
  {
    "ID": 58,
    "相性": 98
  },
  {
    "ID": 59,
    "相性": 101
  },
  {
    "ID": 63,
    "相性": 129
  },
  {
    "ID": 64,
    "相性": 125
  },
  {
    "ID": 65,
    "相性": 126
  },
  {
    "ID": 66,
    "相性": 126
  },
  {
    "ID": 67,
    "相性": 82
  },
  {
    "ID": 68,
    "相性": 96
  },
  {
    "ID": 69,
    "相性": 97
  },
  {
    "ID": 70,
    "相性": 34
  },
  {
    "ID": 71,
    "相性": 92
  },
  {
    "ID": 72,
    "相性": 102
  },
  {
    "ID": 73,
    "相性": 69
  },
  {
    "ID": 74,
    "相性": 25
  },
  {
    "ID": 75,
    "相性": 25
  },
  {
    "ID": 76,
    "相性": 142
  },
  {
    "ID": 78,
    "相性": 85
  },
  {
    "ID": 79,
    "相性": 69
  },
  {
    "ID": 80,
    "相性": 18
  },
  {
    "ID": 81,
    "相性": 102
  },
  {
    "ID": 82,
    "相性": 140
  },
  {
    "ID": 84,
    "相性": 139
  },
  {
    "ID": 85,
    "相性": 101
  },
  {
    "ID": 86,
    "相性": 101
  },
  {
    "ID": 87,
    "相性": 140
  },
  {
    "ID": 88,
    "相性": 86
  },
  {
    "ID": 89,
    "相性": 101
  },
  {
    "ID": 90,
    "相性": 95
  },
  {
    "ID": 91,
    "相性": 140
  },
  {
    "ID": 92,
    "相性": 11
  },
  {
    "ID": 94,
    "相性": 75
  },
  {
    "ID": 95,
    "相性": 148
  },
  {
    "ID": 96,
    "相性": 15
  },
  {
    "ID": 97,
    "相性": 100
  },
  {
    "ID": 98,
    "相性": 56
  },
  {
    "ID": 99,
    "相性": 72
  },
  {
    "ID": 101,
    "相性": 15
  },
  {
    "ID": 102,
    "相性": 141
  },
  {
    "ID": 103,
    "相性": 145
  },
  {
    "ID": 104,
    "相性": 11
  },
  {
    "ID": 105,
    "相性": 36
  },
  {
    "ID": 107,
    "相性": 126
  },
  {
    "ID": 108,
    "相性": 127
  },
  {
    "ID": 109,
    "相性": 25
  },
  {
    "ID": 110,
    "相性": 142
  },
  {
    "ID": 112,
    "相性": 129
  },
  {
    "ID": 113,
    "相性": 8
  },
  {
    "ID": 114,
    "相性": 73
  },
  {
    "ID": 115,
    "相性": 40
  },
  {
    "ID": 116,
    "相性": 48
  },
  {
    "ID": 117,
    "相性": 127
  },
  {
    "ID": 118,
    "相性": 138
  },
  {
    "ID": 119,
    "相性": 94
  },
  {
    "ID": 120,
    "相性": 76
  },
  {
    "ID": 121,
    "相性": 59
  },
  {
    "ID": 122,
    "相性": 43
  },
  {
    "ID": 125,
    "相性": 64
  },
  {
    "ID": 126,
    "相性": 92
  },
  {
    "ID": 127,
    "相性": 13
  },
  {
    "ID": 128,
    "相性": 22
  },
  {
    "ID": 129,
    "相性": 84
  },
  {
    "ID": 130,
    "相性": 37
  },
  {
    "ID": 131,
    "相性": 7
  },
  {
    "ID": 132,
    "相性": 5
  },
  {
    "ID": 133,
    "相性": 10
  },
  {
    "ID": 134,
    "相性": 7
  },
  {
    "ID": 135,
    "相性": 104
  },
  {
    "ID": 136,
    "相性": 138
  },
  {
    "ID": 137,
    "相性": 96
  },
  {
    "ID": 138,
    "相性": 48
  },
  {
    "ID": 139,
    "相性": 44
  },
  {
    "ID": 140,
    "相性": 137
  },
  {
    "ID": 141,
    "相性": 99
  },
  {
    "ID": 143,
    "相性": 76
  },
  {
    "ID": 144,
    "相性": 22
  },
  {
    "ID": 145,
    "相性": 87
  },
  {
    "ID": 146,
    "相性": 22
  },
  {
    "ID": 147,
    "相性": -1
  },
  {
    "ID": 148,
    "相性": 71
  },
  {
    "ID": 149,
    "相性": 25
  },
  {
    "ID": 150,
    "相性": 144
  },
  {
    "ID": 151,
    "相性": 9
  },
  {
    "ID": 152,
    "相性": 148
  },
  {
    "ID": 153,
    "相性": 46
  },
  {
    "ID": 154,
    "相性": 40
  },
  {
    "ID": 155,
    "相性": 23
  },
  {
    "ID": 157,
    "相性": 74
  },
  {
    "ID": 158,
    "相性": 134
  },
  {
    "ID": 160,
    "相性": 57
  },
  {
    "ID": 161,
    "相性": 14
  },
  {
    "ID": 162,
    "相性": 48
  },
  {
    "ID": 163,
    "相性": 122
  },
  {
    "ID": 164,
    "相性": 7
  },
  {
    "ID": 165,
    "相性": 8
  },
  {
    "ID": 166,
    "相性": 83
  },
  {
    "ID": 168,
    "相性": 126
  },
  {
    "ID": 169,
    "相性": 147
  },
  {
    "ID": 170,
    "相性": 24
  },
  {
    "ID": 171,
    "相性": 95
  },
  {
    "ID": 172,
    "相性": 72
  },
  {
    "ID": 173,
    "相性": 101
  },
  {
    "ID": 174,
    "相性": 74
  },
  {
    "ID": 175,
    "相性": 48
  },
  {
    "ID": 176,
    "相性": 39
  },
  {
    "ID": 177,
    "相性": 22
  },
  {
    "ID": 178,
    "相性": 107
  },
  {
    "ID": 179,
    "相性": 68
  },
  {
    "ID": 180,
    "相性": 124
  },
  {
    "ID": 181,
    "相性": 132
  },
  {
    "ID": 182,
    "相性": 136
  },
  {
    "ID": 184,
    "相性": 122
  },
  {
    "ID": 185,
    "相性": 120
  },
  {
    "ID": 186,
    "相性": 36
  },
  {
    "ID": 187,
    "相性": 124
  },
  {
    "ID": 188,
    "相性": 12
  },
  {
    "ID": 189,
    "相性": 89
  },
  {
    "ID": 190,
    "相性": 83
  },
  {
    "ID": 191,
    "相性": 25
  },
  {
    "ID": 192,
    "相性": 27
  },
  {
    "ID": 194,
    "相性": 142
  },
  {
    "ID": 195,
    "相性": 59
  },
  {
    "ID": 196,
    "相性": 48
  },
  {
    "ID": 197,
    "相性": 130
  },
  {
    "ID": 198,
    "相性": 107
  },
  {
    "ID": 199,
    "相性": 108
  },
  {
    "ID": 200,
    "相性": 65
  },
  {
    "ID": 202,
    "相性": 42
  },
  {
    "ID": 203,
    "相性": 12
  },
  {
    "ID": 204,
    "相性": 22
  },
  {
    "ID": 205,
    "相性": 17
  },
  {
    "ID": 206,
    "相性": 27
  },
  {
    "ID": 207,
    "相性": 23
  },
  {
    "ID": 208,
    "相性": 125,
    "标签": ["乐"]
  },
  {
    "ID": 209,
    "相性": 121
  },
  {
    "ID": 210,
    "相性": 12
  },
  {
    "ID": 211,
    "相性": 36
  },
  {
    "ID": 212,
    "相性": 28
  },
  {
    "ID": 213,
    "相性": 79
  },
  {
    "ID": 214,
    "相性": 119
  },
  {
    "ID": 215,
    "相性": 127
  },
  {
    "ID": 216,
    "相性": 21
  },
  {
    "ID": 217,
    "相性": 147
  },
  {
    "ID": 218,
    "相性": 72
  },
  {
    "ID": 219,
    "相性": 22
  },
  {
    "ID": 220,
    "相性": 123
  },
  {
    "ID": 221,
    "相性": 129
  },
  {
    "ID": 222,
    "相性": 123
  },
  {
    "ID": 223,
    "相性": 23
  },
  {
    "ID": 224,
    "相性": 25
  },
  {
    "ID": 225,
    "相性": 36
  },
  {
    "ID": 226,
    "相性": 48
  },
  {
    "ID": 227,
    "相性": 75
  },
  {
    "ID": 228,
    "相性": 75
  },
  {
    "ID": 229,
    "相性": 21
  },
  {
    "ID": 230,
    "相性": 123
  },
  {
    "ID": 231,
    "相性": 126
  },
  {
    "ID": 232,
    "相性": 66
  },
  {
    "ID": 233,
    "相性": 71
  },
  {
    "ID": 234,
    "相性": 74
  },
  {
    "ID": 235,
    "相性": 29
  },
  {
    "ID": 236,
    "相性": 30
  },
  {
    "ID": 237,
    "相性": 147
  },
  {
    "ID": 238,
    "相性": 34
  },
  {
    "ID": 239,
    "相性": 85
  },
  {
    "ID": 240,
    "相性": 21
  },
  {
    "ID": 241,
    "相性": 128
  },
  {
    "ID": 242,
    "相性": 121
  },
  {
    "ID": 243,
    "相性": 16
  },
  {
    "ID": 244,
    "相性": 77
  },
  {
    "ID": 245,
    "相性": 148
  },
  {
    "ID": 246,
    "相性": 36
  },
  {
    "ID": 247,
    "相性": 124
  },
  {
    "ID": 248,
    "相性": 29
  },
  {
    "ID": 250,
    "相性": 147
  },
  {
    "ID": 251,
    "相性": 80
  },
  {
    "ID": 252,
    "相性": 17
  },
  {
    "ID": 253,
    "相性": 39
  },
  {
    "ID": 254,
    "相性": 126
  },
  {
    "ID": 255,
    "相性": 7
  },
  {
    "ID": 256,
    "相性": 90
  },
  {
    "ID": 257,
    "相性": 7
  },
  {
    "ID": 258,
    "相性": 88
  },
  {
    "ID": 259,
    "相性": 7
  },
  {
    "ID": 260,
    "相性": 25
  },
  {
    "ID": 261,
    "相性": 55
  },
  {
    "ID": 264,
    "相性": 142
  },
  {
    "ID": 266,
    "相性": 145
  },
  {
    "ID": 267,
    "相性": 76
  },
  {
    "ID": 269,
    "相性": 26
  },
  {
    "ID": 270,
    "相性": 142
  },
  {
    "ID": 272,
    "相性": 65
  },
  {
    "ID": 273,
    "相性": 70
  },
  {
    "ID": 274,
    "相性": 138
  },
  {
    "ID": 275,
    "相性": 70
  },
  {
    "ID": 276,
    "相性": 23
  },
  {
    "ID": 277,
    "相性": 70
  },
  {
    "ID": 278,
    "相性": 124
  },
  {
    "ID": 279,
    "相性": 124
  },
  {
    "ID": 280,
    "相性": 53
  },
  {
    "ID": 281,
    "相性": 55
  },
  {
    "ID": 282,
    "相性": 20
  },
  {
    "ID": 283,
    "相性": 30
  },
  {
    "ID": 284,
    "相性": 43
  },
  {
    "ID": 285,
    "相性": 121
  },
  {
    "ID": 286,
    "相性": 22
  },
  {
    "ID": 287,
    "相性": 124
  },
  {
    "ID": 288,
    "相性": 36
  },
  {
    "ID": 290,
    "相性": 28
  },
  {
    "ID": 291,
    "相性": 29
  },
  {
    "ID": 292,
    "相性": 120
  },
  {
    "ID": 293,
    "相性": 125
  },
  {
    "ID": 294,
    "相性": 31
  },
  {
    "ID": 297,
    "相性": 53
  },
  {
    "ID": 299,
    "相性": 67
  },
  {
    "ID": 300,
    "相性": 124
  },
  {
    "ID": 301,
    "相性": 21
  },
  {
    "ID": 302,
    "相性": 29
  },
  {
    "ID": 303,
    "相性": 27
  },
  {
    "ID": 304,
    "相性": 72
  },
  {
    "ID": 305,
    "相性": 128
  },
  {
    "ID": 306,
    "相性": 29
  },
  {
    "ID": 307,
    "相性": 79
  },
  {
    "ID": 308,
    "相性": 125
  },
  {
    "ID": 309,
    "相性": 75
  },
  {
    "ID": 311,
    "相性": 132
  },
  {
    "ID": 312,
    "相性": 32
  },
  {
    "ID": 313,
    "相性": 24
  },
  {
    "ID": 314,
    "相性": 72
  },
  {
    "ID": 315,
    "相性": 44
  },
  {
    "ID": 316,
    "相性": 70
  },
  {
    "ID": 317,
    "相性": 121
  },
  {
    "ID": 318,
    "相性": 31
  },
  {
    "ID": 319,
    "相性": 25
  },
  {
    "ID": 321,
    "相性": 74
  },
  {
    "ID": 322,
    "相性": 21
  },
  {
    "ID": 324,
    "相性": 29
  },
  {
    "ID": 325,
    "相性": 20
  },
  {
    "ID": 326,
    "相性": 73
  },
  {
    "ID": 327,
    "相性": 108
  },
  {
    "ID": 328,
    "相性": 27
  },
  {
    "ID": 329,
    "相性": 34
  },
  {
    "ID": 330,
    "相性": 127
  },
  {
    "ID": 331,
    "相性": 128
  },
  {
    "ID": 332,
    "相性": 24
  },
  {
    "ID": 333,
    "相性": 22
  },
  {
    "ID": 334,
    "相性": 26
  },
  {
    "ID": 335,
    "相性": 127
  },
  {
    "ID": 336,
    "相性": 21
  },
  {
    "ID": 337,
    "相性": 122
  },
  {
    "ID": 338,
    "相性": 71
  },
  {
    "ID": 339,
    "相性": 129,
    "标签": ["乐"]
  },
  {
    "ID": 340,
    "相性": 54
  },
  {
    "ID": 342,
    "相性": 56
  },
  {
    "ID": 343,
    "相性": 132
  },
  {
    "ID": 344,
    "相性": 26,
    "标签": ["乐"]
  },
  {
    "ID": 345,
    "相性": 19
  },
  {
    "ID": 346,
    "相性": 75,
    "标签": ["乐"]
  },
  {
    "ID": 347,
    "相性": 126
  },
  {
    "ID": 348,
    "相性": 69
  },
  {
    "ID": 349,
    "相性": 20
  },
  {
    "ID": 350,
    "相性": 45
  },
  {
    "ID": 351,
    "相性": 75
  },
  {
    "ID": 352,
    "相性": 74
  },
  {
    "ID": 353,
    "相性": 71
  },
  {
    "ID": 354,
    "相性": 25
  },
  {
    "ID": 355,
    "相性": 122
  },
  {
    "ID": 356,
    "相性": 124
  },
  {
    "ID": 357,
    "相性": 78
  },
  {
    "ID": 358,
    "相性": 37
  },
  {
    "ID": 359,
    "相性": 33
  },
  {
    "ID": 360,
    "相性": 68
  },
  {
    "ID": 361,
    "相性": 73
  },
  {
    "ID": 362,
    "相性": 52
  },
  {
    "ID": 363,
    "相性": 25,
    "标签": ["乐"]
  },
  {
    "ID": 364,
    "相性": 75,
    "标签": ["乐"]
  },
  {
    "ID": 365,
    "相性": 124
  },
  {
    "ID": 366,
    "相性": 54
  },
  {
    "ID": 367,
    "相性": 32
  },
  {
    "ID": 368,
    "相性": 68
  },
  {
    "ID": 369,
    "相性": 123
  },
  {
    "ID": 371,
    "相性": 77
  },
  {
    "ID": 372,
    "相性": 61
  },
  {
    "ID": 373,
    "相性": 128
  },
  {
    "ID": 374,
    "相性": 37
  },
  {
    "ID": 375,
    "相性": 52
  },
  {
    "ID": 376,
    "相性": 80
  },
  {
    "ID": 377,
    "相性": 81
  },
  {
    "ID": 378,
    "相性": 69
  },
  {
    "ID": 379,
    "相性": 25
  },
  {
    "ID": 380,
    "相性": 71
  },
  {
    "ID": 381,
    "相性": 118
  },
  {
    "ID": 383,
    "相性": 76
  },
  {
    "ID": 384,
    "相性": 23
  },
  {
    "ID": 385,
    "相性": 34
  },
  {
    "ID": 386,
    "相性": 69
  },
  {
    "ID": 387,
    "相性": 63
  },
  {
    "ID": 388,
    "相性": 77
  },
  {
    "ID": 389,
    "相性": 123
  },
  {
    "ID": 391,
    "相性": 79
  },
  {
    "ID": 393,
    "相性": 23
  },
  {
    "ID": 394,
    "相性": 75
  },
  {
    "ID": 395,
    "相性": 78
  },
  {
    "ID": 396,
    "相性": 63
  },
  {
    "ID": 397,
    "相性": 19
  },
  {
    "ID": 398,
    "相性": 41
  },
  {
    "ID": 400,
    "相性": 26
  },
  {
    "ID": 401,
    "相性": 75
  },
  {
    "ID": 402,
    "相性": 26
  },
  {
    "ID": 403,
    "相性": 123
  },
  {
    "ID": 406,
    "相性": 75
  },
  {
    "ID": 407,
    "相性": 21
  },
  {
    "ID": 408,
    "相性": 38
  },
  {
    "ID": 409,
    "相性": 23
  },
  {
    "ID": 412,
    "相性": 118
  },
  {
    "ID": 413,
    "相性": 20
  },
  {
    "ID": 414,
    "相性": 128
  },
  {
    "ID": 415,
    "相性": 28
  },
  {
    "ID": 416,
    "相性": 19
  },
  {
    "ID": 417,
    "相性": 26
  },
  {
    "ID": 418,
    "相性": 30
  },
  {
    "ID": 420,
    "相性": 136
  },
  {
    "ID": 422,
    "相性": 121
  },
  {
    "ID": 423,
    "相性": 39
  },
  {
    "ID": 424,
    "相性": 81
  },
  {
    "ID": 425,
    "相性": 120
  },
  {
    "ID": 426,
    "相性": 116
  },
  {
    "ID": 427,
    "相性": 130
  },
  {
    "ID": 428,
    "相性": 26
  },
  {
    "ID": 429,
    "相性": 65
  },
  {
    "ID": 431,
    "相性": 10
  },
  {
    "ID": 432,
    "相性": 60
  },
  {
    "ID": 434,
    "相性": 126
  },
  {
    "ID": 435,
    "相性": 73
  },
  {
    "ID": 436,
    "相性": 73
  },
  {
    "ID": 437,
    "相性": 24
  },
  {
    "ID": 440,
    "相性": 25
  },
  {
    "ID": 441,
    "相性": 60
  },
  {
    "ID": 442,
    "相性": 135
  },
  {
    "ID": 443,
    "相性": 129
  },
  {
    "ID": 444,
    "相性": 76
  },
  {
    "ID": 446,
    "相性": 60
  },
  {
    "ID": 447,
    "相性": 19
  },
  {
    "ID": 448,
    "相性": 132
  },
  {
    "ID": 449,
    "相性": 67
  },
  {
    "ID": 450,
    "相性": 78
  },
  {
    "ID": 451,
    "相性": 51
  },
  {
    "ID": 453,
    "相性": 23
  },
  {
    "ID": 454,
    "相性": 20
  },
  {
    "ID": 455,
    "相性": 31
  },
  {
    "ID": 456,
    "相性": 125
  },
  {
    "ID": 457,
    "相性": 75
  },
  {
    "ID": 458,
    "相性": 28
  },
  {
    "ID": 459,
    "相性": 28
  },
  {
    "ID": 460,
    "相性": 75
  },
  {
    "ID": 461,
    "相性": 31
  },
  {
    "ID": 462,
    "相性": 39
  },
  {
    "ID": 463,
    "相性": 130
  },
  {
    "ID": 464,
    "相性": 23
  },
  {
    "ID": 466,
    "相性": 74
  },
  {
    "ID": 467,
    "相性": 78
  },
  {
    "ID": 468,
    "相性": 121
  },
  {
    "ID": 469,
    "相性": 129
  },
  {
    "ID": 470,
    "相性": 32
  },
  {
    "ID": 471,
    "相性": 31
  },
  {
    "ID": 472,
    "相性": 29
  },
  {
    "ID": 473,
    "相性": 41
  },
  {
    "ID": 474,
    "相性": 75
  },
  {
    "ID": 475,
    "相性": 76
  },
  {
    "ID": 476,
    "相性": 129
  },
  {
    "ID": 477,
    "相性": 38
  },
  {
    "ID": 478,
    "相性": 20
  },
  {
    "ID": 479,
    "相性": 125
  },
  {
    "ID": 480,
    "相性": 115
  },
  {
    "ID": 481,
    "相性": 75
  },
  {
    "ID": 482,
    "相性": 22
  },
  {
    "ID": 483,
    "相性": 40
  },
  {
    "ID": 484,
    "相性": 31
  },
  {
    "ID": 485,
    "相性": 33
  },
  {
    "ID": 486,
    "相性": 26
  },
  {
    "ID": 487,
    "相性": 20
  },
  {
    "ID": 488,
    "相性": 30
  },
  {
    "ID": 489,
    "相性": 122
  },
  {
    "ID": 490,
    "相性": 31
  },
  {
    "ID": 491,
    "相性": 38
  },
  {
    "ID": 492,
    "相性": 126
  },
  {
    "ID": 493,
    "相性": 32
  },
  {
    "ID": 494,
    "相性": 22,
    "标签": ["乐"]
  },
  {
    "ID": 495,
    "相性": 62
  },
  {
    "ID": 496,
    "相性": 128
  },
  {
    "ID": 497,
    "相性": 41
  },
  {
    "ID": 498,
    "相性": 125
  },
  {
    "ID": 499,
    "相性": 116
  },
  {
    "ID": 500,
    "相性": 126
  },
  {
    "ID": 501,
    "相性": 32
  },
  {
    "ID": 502,
    "相性": 115
  },
  {
    "ID": 503,
    "相性": 117
  },
  {
    "ID": 504,
    "相性": 31
  },
  {
    "ID": 505,
    "相性": 125
  },
  {
    "ID": 506,
    "相性": 24
  },
  {
    "ID": 507,
    "相性": 75
  },
  {
    "ID": 508,
    "相性": 114
  },
  {
    "ID": 509,
    "相性": 26
  },
  {
    "ID": 510,
    "相性": 62
  },
  {
    "ID": 512,
    "相性": 72
  },
  {
    "ID": 513,
    "相性": 35
  },
  {
    "ID": 514,
    "相性": 62
  },
  {
    "ID": 515,
    "相性": 20
  },
  {
    "ID": 518,
    "相性": 62
  },
  {
    "ID": 520,
    "相性": 121
  },
  {
    "ID": 521,
    "相性": 106
  },
  {
    "ID": 523,
    "相性": 51
  },
  {
    "ID": 524,
    "相性": 25
  },
  {
    "ID": 525,
    "相性": 75
  },
  {
    "ID": 526,
    "相性": 125,
    "标签": ["乐"]
  },
  {
    "ID": 527,
    "相性": 125
  },
  {
    "ID": 528,
    "相性": 125
  },
  {
    "ID": 529,
    "相性": 25
  },
  {
    "ID": 530,
    "相性": 60
  },
  {
    "ID": 531,
    "相性": 43,
    "标签": ["乐"]
  },
  {
    "ID": 533,
    "相性": 66
  },
  {
    "ID": 534,
    "相性": 22,
    "标签": ["乐"]
  },
  {
    "ID": 535,
    "相性": 4,
    "标签": ["乐"]
  },
  {
    "ID": 536,
    "相性": 7
  },
  {
    "ID": 537,
    "相性": 7
  },
  {
    "ID": 538,
    "相性": 131
  },
  {
    "ID": 542,
    "相性": 127
  },
  {
    "ID": 543,
    "相性": 126
  },
  {
    "ID": 545,
    "相性": 125
  },
  {
    "ID": 547,
    "相性": 75
  },
  {
    "ID": 548,
    "相性": 80
  },
  {
    "ID": 549,
    "相性": 60
  },
  {
    "ID": 551,
    "相性": 31
  },
  {
    "ID": 553,
    "相性": 74
  },
  {
    "ID": 555,
    "相性": 56
  },
  {
    "ID": 556,
    "相性": 76
  },
  {
    "ID": 557,
    "相性": 75
  },
  {
    "ID": 558,
    "相性": 145
  },
  {
    "ID": 559,
    "相性": 75
  }
]
