[
  {
    "ID": 0,
    "名称": "纶巾",
    "品质": 1,
    "攻击力": 0,
    "防御力": 4,
    "重量": 2,
    "价格": 50,
    "图像": 40
  },
  {
    "ID": 1,
    "名称": "兜鍪",
    "品质": 2,
    "攻击力": 0,
    "防御力": "5",
    "重量": 4,
    "价格": 80,
    "图像": 41
  },
  {
    "ID": 2,
    "名称": "硬皮",
    "品质": 3,
    "攻击力": 0,
    "防御力": "7",
    "重量": 6,
    "价格": 100,
    "图像": 42
  },
  {
    "ID": 3,
    "名称": "鹤氅",
    "品质": 4,
    "攻击力": 0,
    "防御力": "8",
    "重量": 5,
    "价格": 150,
    "图像": 43
  },
  {
    "ID": 4,
    "名称": "甲胄",
    "品质": 5,
    "攻击力": 0,
    "防御力": 9,
    "重量": 8,
    "价格": 200,
    "图像": 44
  },
  {
    "ID": 5,
    "名称": "废铁甲",
    "品质": 1,
    "攻击力": 0,
    "防御力": 1,
    "重量": 1,
    "价格": 0,
    "图像": 45,
    "描述": "传说以前是个非常强的防具。"
  },
  {
    "ID": 6,
    "名称": "圣者衣",
    "品质": "S",
    "攻击力": 0,
    "防御力": 11,
    "重量": 3,
    "价格": 350,
    "图像": 46,
    "数量": 1,
    "购买条件": "a.德>=90",
    "特性": [{ "全计策": 1 }]
  },
  {
    "ID": 7,
    "名称": "龙鳞铠",
    "品质": "S",
    "攻击力": 0,
    "防御力": 12,
    "重量": 10,
    "价格": 400,
    "图像": 47,
    "数量": 1,
    "特性": [{ "每日回体": 10 }]
  },
  {
    "ID": 8,
    "名称": "兽面吞头铠",
    "品质": "S",
    "攻击力": 0,
    "防御力": 13,
    "重量": 10,
    "价格": 400,
    "数量": 1,
    "图像": 48,
    "特性": [
      {
        "白兵动态胆": 1,
        "公式": "min(99, get_power())",
        "条件": "get_power()>get_courage()"
      }
    ]
  },
  {
    "ID": 9,
    "名称": "兽带狮盔",
    "品质": "S",
    "攻击力": 0,
    "防御力": 11,
    "重量": 4,
    "价格": 400,
    "数量": 1,
    "特性": [{ "单挑免死": 2 }],
    "图像": 49
  },
  {
    "ID": 10,
    "名称": "废铁盔",
    "显示名": "废铁盔",
    "品质": 1,
    "攻击力": 0,
    "防御力": 0,
    "重量": 0,
    "价格": 400,
    "数量": 1,
    "图像": 50,
    "描述": "曾经是蕴含野兽力量的神器残骸。\n现在只是个纪念品而已。"
  },
  {
    "ID": 11,
    "名称": "爛银铠",
    "品质": "S",
    "攻击力": 0,
    "防御力": 12,
    "重量": 12,
    "价格": 400,
    "数量": 1,
    "图像": 96,
    "特性": [
      { "附加体上限": 10 },
      { "白刃战动态胆": "5", "条件": "continuous_tactic_on()" }
    ]
  },
  {
    "ID": 12,
    "名称": "赤帻",
    "品质": "S",
    "攻击力": 0,
    "防御力": 9,
    "重量": 1,
    "价格": 400,
    "图像": 102,
    "数量": 1,
    "解锁条件": [{ "描述": "对孙坚发动【换帻】时获得" }],
    "特性": [
      { "白刃战动态胆": 10 },
      { "白刃战回体": 5, "条件": "is_battle_defender()" }
    ],
    "描述": "获得方式：对孙坚首次发动【换帻】时换装。"
  },
  {
    "ID": 13,
    "名称": "鱼鳞甲",
    "品质": "S",
    "攻击力": 0,
    "防御力": 10,
    "重量": 5,
    "价格": 400,
    "图像": 124,
    "数量": 1,
    "特性": [
      {
        "白刃战初始护甲": 1,
        "公式": "max(1,int((get_politics() - 50) / 5))"
      }
    ]
  },
  {
    "ID": 14,
    "名称": "掩心镜",
    "品质": "S",
    "攻击力": 0,
    "防御力": 4,
    "图像": 126,
    "重量": 1,
    "价格": 400,
    "数量": 1,
    "购买条件描述": "仅赵云和刘禅二人出战时，自动解锁",
    "自动解锁": 1,
    "特性": [{ "白刃战最大受伤": 6, "条件": "get_hp() < 50" }],
    "描述": "赵云所赠，危急时，或能保命？"
  }
]
